tesylocal/__init__.py
tesylocal-1.4.1.dist-info/LICENCE
tesylocal-1.4.1.dist-info/METADATA
tesylocal-1.4.1.dist-info/WHEEL
tesylocal-1.4.1.dist-info/top_level.txt
tesylocal-1.4.1.dist-info/RECORD
