Metadata-Version: 2.1
Name: tesylocal
Version: 1.4.1
Summary: Connect to a Tesy Boiler without the use of the modeco cloud.
Home-page: https://github.com/william-sy/TesyLocal
Author: William
Author-email: wvanbeek.sy@gmail.com
License: GPL-3.0-only
Keywords: Tesy,Modeco,Local
Classifier: Topic :: Utilities
Classifier: License :: OSI Approved :: GNU General Public License v3 or later (GPLv3+)
Classifier: Operating System :: OS Independent
Classifier: Development Status :: 4 - Beta
License-File: LICENCE
Requires-Dist: websocket-client
Requires-Dist: dpath
Requires-Dist: ipaddress
